tests/__init__.py
tests/test_utils.py
transpy/__init__.py
transpy/_version.py
transpy/utils.py
transpy-2020.9.1.dist-info/LICENSE
transpy-2020.9.1.dist-info/METADATA
transpy-2020.9.1.dist-info/WHEEL
transpy-2020.9.1.dist-info/top_level.txt
transpy-2020.9.1.dist-info/RECORD
